pad_analytics/__init__.py
pad_analytics/dataset_manager.py
pad_analytics/fileManagement.py
pad_analytics/intensityFind.py
pad_analytics/pad_analysis.py
pad_analytics/pad_helper.py
pad_analytics/padanalytics.py
pad_analytics/pixelProcessing.py
pad_analytics/pls_model.py
pad_analytics/py.typed
pad_analytics/regionRoutine.py
pad_analytics/data/model_dataset_mapping.csv
pad_analytics-0.2.2.dist-info/LICENSE
pad_analytics-0.2.2.dist-info/METADATA
pad_analytics-0.2.2.dist-info/WHEEL
pad_analytics-0.2.2.dist-info/entry_points.txt
pad_analytics-0.2.2.dist-info/top_level.txt
pad_analytics-0.2.2.dist-info/RECORD
