Metadata-Version: 2.1
Name: pad-analytics
Version: 0.2.2
Summary: Python tools for analyzing Paper Analytical Devices (PADs) to detect and quantify pharmaceutical compounds through colorimetric analysis
Home-page: https://github.com/PaperAnalyticalDeviceND/pad-analytics
Author: Paper Analytical Device Project Team
Author-email: Priscila Saboia Moreira <pmoreira@nd.edu>
License: MIT
Project-URL: Homepage, https://padproject.nd.edu
Project-URL: Documentation, https://pad.crc.nd.edu/docs
Project-URL: Repository, https://github.com/PaperAnalyticalDeviceND/pad-analytics
Project-URL: Issues, https://github.com/PaperAnalyticalDeviceND/pad-analytics/issues
Project-URL: Source Code, https://github.com/PaperAnalyticalDeviceND/pad-analytics
Keywords: paper analytical device,PAD,colorimetric analysis,pharmaceutical quality,drug detection,machine learning,diagnostics
Classifier: Development Status :: 4 - Beta
Classifier: Intended Audience :: Science/Research
Classifier: Intended Audience :: Healthcare Industry
Classifier: Topic :: Scientific/Engineering :: Artificial Intelligence
Classifier: Topic :: Scientific/Engineering :: Chemistry
Classifier: Topic :: Scientific/Engineering :: Medical Science Apps.
Classifier: Programming Language :: Python :: 3
Classifier: Programming Language :: Python :: 3.9
Classifier: Programming Language :: Python :: 3.10
Classifier: Programming Language :: Python :: 3.11
Classifier: Operating System :: OS Independent
Requires-Python: >=3.8
License-File: LICENSE
Requires-Dist: keras>=2.14.0
Requires-Dist: tensorflow>=2.14.0
Requires-Dist: pandas>=1.3.0
Requires-Dist: numpy>=1.21.0
Requires-Dist: scikit-learn>=0.24.0
Requires-Dist: matplotlib>=3.3.0
Requires-Dist: seaborn>=0.11.0
Requires-Dist: requests>=2.32.2
Requires-Dist: pillow>=8.0.0
Requires-Dist: opencv-python>=4.5.0
Requires-Dist: ipywidgets>=7.6.0
Requires-Dist: importlib-resources>=1.3.0; python_version < "3.9"
Provides-Extra: dev
Requires-Dist: pytest>=6.0; extra == "dev"
Requires-Dist: pytest-cov>=2.0; extra == "dev"
Requires-Dist: pytest-mock>=3.0; extra == "dev"
Requires-Dist: black>=21.0; extra == "dev"
Requires-Dist: flake8>=3.9; extra == "dev"
Requires-Dist: mypy>=0.910; extra == "dev"
Requires-Dist: safety>=1.10.0; extra == "dev"
Requires-Dist: bandit>=1.7.0; extra == "dev"
Requires-Dist: build>=0.8.0; extra == "dev"
Requires-Dist: twine>=4.0.0; extra == "dev"
Provides-Extra: notebooks
Requires-Dist: jupyter>=1.0.0; extra == "notebooks"
Requires-Dist: notebook>=6.0.0; extra == "notebooks"
Requires-Dist: ipykernel>=6.0.0; extra == "notebooks"
